Metadata-Version: 2.4
Name: econml
Version: 0.16.0
Summary: This package contains several methods for calculating Conditional Average Treatment Effects
Author: PyWhy contributors
License-Expression: MIT
Project-URL: Homepage, https://github.com/py-why/EconML
Project-URL: Bug Tracker, https://github.com/py-why/EconML/Issues
Project-URL: Source Code, https://github.com/py-why/EconML
Project-URL: Documentation, https://econml.azurewebsites.net/
Keywords: treatment-effect
Classifier: Programming Language :: Python :: 3.9
Classifier: Programming Language :: Python :: 3.10
Classifier: Programming Language :: Python :: 3.11
Classifier: Programming Language :: Python :: 3.12
Classifier: Programming Language :: Python :: 3.13
Classifier: Operating System :: MacOS
Classifier: Operating System :: Microsoft :: Windows
Classifier: Operating System :: POSIX :: Linux
Requires-Python: >=3.9
License-File: LICENSE
Requires-Dist: numpy
Requires-Dist: scipy>1.4.0
Requires-Dist: scikit-learn<1.7,>=1.0
Requires-Dist: sparse
Requires-Dist: joblib>=0.13.0
Requires-Dist: statsmodels>=0.10
Requires-Dist: pandas>1.0
Requires-Dist: shap<0.49.0,>=0.38.1
Requires-Dist: lightgbm
Requires-Dist: packaging
Provides-Extra: automl
Requires-Dist: azure-cli; extra == "automl"
Provides-Extra: plt
Requires-Dist: graphviz; extra == "plt"
Requires-Dist: matplotlib; extra == "plt"
Provides-Extra: dowhy
Requires-Dist: dowhy<0.13; extra == "dowhy"
Provides-Extra: ray
Requires-Dist: ray>2.2.0; extra == "ray"
Provides-Extra: all
Requires-Dist: azure-cli; extra == "all"
Requires-Dist: graphviz; extra == "all"
Requires-Dist: matplotlib; extra == "all"
Requires-Dist: dowhy<0.13; extra == "all"
Requires-Dist: ray>2.2.0; extra == "all"
Dynamic: license-file
